{
  "hook_type": "async",
  "gpu_index": 0,
  "sample_interval_sec": 0.5,
  "summary": {
    "sample_count": 161,
    "duration_sec": 83.97677753027529,
    "avg_power_w": 145.26559006211176,
    "peak_power_w": 216.12,
    "energy_j": 12196.800106898052
  },
  "error": null,
  "samples": [
    {
      "time_sec": 0.02210957184433937,
      "power_w": 137.55
    },
    {
      "time_sec": 0.5435780817642808,
      "power_w": 117.81
    },
    {
      "time_sec": 1.0659427093341947,
      "power_w": 116.75
    },
    {
      "time_sec": 1.588254053145647,
      "power_w": 116.61
    },
    {
      "time_sec": 2.112251343205571,
      "power_w": 110.75
    },
    {
      "time_sec": 2.636816737242043,
      "power_w": 89.61
    },
    {
      "time_sec": 3.163637916557491,
      "power_w": 75.93
    },
    {
      "time_sec": 3.6892177807167172,
      "power_w": 75.06
    },
    {
      "time_sec": 4.21399063616991,
      "power_w": 74.46
    },
    {
      "time_sec": 4.7394125908613205,
      "power_w": 74.05
    },
    {
      "time_sec": 5.2633569575846195,
      "power_w": 73.96
    },
    {
      "time_sec": 5.786824204958975,
      "power_w": 73.97
    },
    {
      "time_sec": 6.311151708476245,
      "power_w": 74.0
    },
    {
      "time_sec": 6.835724885575473,
      "power_w": 74.03
    },
    {
      "time_sec": 7.361863844096661,
      "power_w": 73.99
    },
    {
      "time_sec": 7.8861623564735055,
      "power_w": 73.92
    },
    {
      "time_sec": 8.41107150632888,
      "power_w": 73.94
    },
    {
      "time_sec": 8.934867177158594,
      "power_w": 73.95
    },
    {
      "time_sec": 9.458275980316103,
      "power_w": 73.94
    },
    {
      "time_sec": 9.98238171543926,
      "power_w": 73.94
    },
    {
      "time_sec": 10.506473803892732,
      "power_w": 73.98
    },
    {
      "time_sec": 11.030006564222276,
      "power_w": 74.03
    },
    {
      "time_sec": 11.606082811020315,
      "power_w": 74.06
    },
    {
      "time_sec": 12.132457566447556,
      "power_w": 74.03
    },
    {
      "time_sec": 12.659799905493855,
      "power_w": 74.02
    },
    {
      "time_sec": 13.185652629472315,
      "power_w": 73.95
    },
    {
      "time_sec": 13.711953272111714,
      "power_w": 73.97
    },
    {
      "time_sec": 14.239229019731283,
      "power_w": 74.05
    },
    {
      "time_sec": 14.766731355339289,
      "power_w": 74.01
    },
    {
      "time_sec": 15.293394566513598,
      "power_w": 73.97
    },
    {
      "time_sec": 15.819257688708603,
      "power_w": 73.96
    },
    {
      "time_sec": 16.345414432696998,
      "power_w": 73.92
    },
    {
      "time_sec": 16.87324680853635,
      "power_w": 74.03
    },
    {
      "time_sec": 17.400999990291893,
      "power_w": 74.12
    },
    {
      "time_sec": 17.927932794205844,
      "power_w": 74.02
    },
    {
      "time_sec": 18.453812448307872,
      "power_w": 73.92
    },
    {
      "time_sec": 18.98507146909833,
      "power_w": 73.95
    },
    {
      "time_sec": 19.52291176095605,
      "power_w": 73.94
    },
    {
      "time_sec": 20.05693554505706,
      "power_w": 73.98
    },
    {
      "time_sec": 20.581471835263073,
      "power_w": 73.93
    },
    {
      "time_sec": 21.12897981610149,
      "power_w": 73.89
    },
    {
      "time_sec": 21.650912757962942,
      "power_w": 94.06
    },
    {
      "time_sec": 22.17229736223817,
      "power_w": 112.54
    },
    {
      "time_sec": 22.69425847567618,
      "power_w": 112.19
    },
    {
      "time_sec": 23.217187327332795,
      "power_w": 112.54
    },
    {
      "time_sec": 23.739191689528525,
      "power_w": 134.29
    },
    {
      "time_sec": 24.261990131810308,
      "power_w": 153.83
    },
    {
      "time_sec": 24.784682247787714,
      "power_w": 164.22
    },
    {
      "time_sec": 25.306306005455554,
      "power_w": 178.87
    },
    {
      "time_sec": 25.828586648218334,
      "power_w": 185.03
    },
    {
      "time_sec": 26.350672414526343,
      "power_w": 186.66
    },
    {
      "time_sec": 26.873886140994728,
      "power_w": 159.61
    },
    {
      "time_sec": 27.395552223548293,
      "power_w": 146.76
    },
    {
      "time_sec": 27.91800080984831,
      "power_w": 154.29
    },
    {
      "time_sec": 28.440166495740414,
      "power_w": 176.78
    },
    {
      "time_sec": 28.9619232499972,
      "power_w": 191.47
    },
    {
      "time_sec": 29.48383429273963,
      "power_w": 185.21
    },
    {
      "time_sec": 30.00694816187024,
      "power_w": 167.83
    },
    {
      "time_sec": 30.528898070566356,
      "power_w": 162.49
    },
    {
      "time_sec": 31.0523495497182,
      "power_w": 162.05
    },
    {
      "time_sec": 31.574321755208075,
      "power_w": 172.05
    },
    {
      "time_sec": 32.09737045224756,
      "power_w": 168.59
    },
    {
      "time_sec": 32.62079184874892,
      "power_w": 178.33
    },
    {
      "time_sec": 33.143868926912546,
      "power_w": 181.49
    },
    {
      "time_sec": 33.66658316832036,
      "power_w": 170.0
    },
    {
      "time_sec": 34.18882804643363,
      "power_w": 173.01
    },
    {
      "time_sec": 34.71081230323762,
      "power_w": 188.25
    },
    {
      "time_sec": 35.23288688156754,
      "power_w": 180.18
    },
    {
      "time_sec": 35.75588014628738,
      "power_w": 171.78
    },
    {
      "time_sec": 36.2803985401988,
      "power_w": 179.05
    },
    {
      "time_sec": 36.8021521223709,
      "power_w": 178.59
    },
    {
      "time_sec": 37.32383614126593,
      "power_w": 181.93
    },
    {
      "time_sec": 37.8721808642149,
      "power_w": 164.99
    },
    {
      "time_sec": 38.39493019785732,
      "power_w": 126.77
    },
    {
      "time_sec": 38.94322147406638,
      "power_w": 113.24
    },
    {
      "time_sec": 39.48353096842766,
      "power_w": 113.13
    },
    {
      "time_sec": 40.00665708724409,
      "power_w": 140.48
    },
    {
      "time_sec": 40.528829474933445,
      "power_w": 157.29
    },
    {
      "time_sec": 41.050480933859944,
      "power_w": 150.76
    },
    {
      "time_sec": 41.57246403582394,
      "power_w": 143.81
    },
    {
      "time_sec": 42.094541696831584,
      "power_w": 140.35
    },
    {
      "time_sec": 42.61630353331566,
      "power_w": 166.79
    },
    {
      "time_sec": 43.138905172236264,
      "power_w": 180.62
    },
    {
      "time_sec": 43.66118005942553,
      "power_w": 176.49
    },
    {
      "time_sec": 44.18353778868914,
      "power_w": 164.99
    },
    {
      "time_sec": 44.70614658202976,
      "power_w": 177.24
    },
    {
      "time_sec": 45.22883648891002,
      "power_w": 170.32
    },
    {
      "time_sec": 45.75157778337598,
      "power_w": 191.18
    },
    {
      "time_sec": 46.27407506201416,
      "power_w": 198.83
    },
    {
      "time_sec": 46.796684458851814,
      "power_w": 179.27
    },
    {
      "time_sec": 47.320093433372676,
      "power_w": 191.21
    },
    {
      "time_sec": 47.84168803226203,
      "power_w": 188.73
    },
    {
      "time_sec": 48.363558296114206,
      "power_w": 171.9
    },
    {
      "time_sec": 48.88563436456025,
      "power_w": 169.03
    },
    {
      "time_sec": 49.408795380964875,
      "power_w": 176.61
    },
    {
      "time_sec": 49.93044338282198,
      "power_w": 202.37
    },
    {
      "time_sec": 50.45253875758499,
      "power_w": 208.32
    },
    {
      "time_sec": 50.973888096399605,
      "power_w": 193.38
    },
    {
      "time_sec": 51.495289186015725,
      "power_w": 186.59
    },
    {
      "time_sec": 52.01858135778457,
      "power_w": 187.92
    },
    {
      "time_sec": 52.54555635340512,
      "power_w": 194.93
    },
    {
      "time_sec": 53.06829479429871,
      "power_w": 154.96
    },
    {
      "time_sec": 53.59005653299391,
      "power_w": 113.68
    },
    {
      "time_sec": 54.1129679614678,
      "power_w": 131.68
    },
    {
      "time_sec": 54.63521401397884,
      "power_w": 152.24
    },
    {
      "time_sec": 55.15904793422669,
      "power_w": 162.13
    },
    {
      "time_sec": 55.68270526546985,
      "power_w": 172.76
    },
    {
      "time_sec": 56.20493201445788,
      "power_w": 167.09
    },
    {
      "time_sec": 56.727641333825886,
      "power_w": 161.0
    },
    {
      "time_sec": 57.25047710631043,
      "power_w": 170.21
    },
    {
      "time_sec": 57.773357947357,
      "power_w": 179.2
    },
    {
      "time_sec": 58.296323124319315,
      "power_w": 179.02
    },
    {
      "time_sec": 58.81908802874386,
      "power_w": 190.04
    },
    {
      "time_sec": 59.341707685031,
      "power_w": 211.59
    },
    {
      "time_sec": 59.86384618189186,
      "power_w": 216.12
    },
    {
      "time_sec": 60.38518655858934,
      "power_w": 194.67
    },
    {
      "time_sec": 60.908146725967526,
      "power_w": 159.2
    },
    {
      "time_sec": 61.43034512270242,
      "power_w": 164.35
    },
    {
      "time_sec": 61.95329474285245,
      "power_w": 165.65
    },
    {
      "time_sec": 62.476002575829625,
      "power_w": 181.12
    },
    {
      "time_sec": 63.0478894347325,
      "power_w": 187.37
    },
    {
      "time_sec": 63.56987751554698,
      "power_w": 180.42
    },
    {
      "time_sec": 64.09251152630895,
      "power_w": 193.19
    },
    {
      "time_sec": 64.61538538429886,
      "power_w": 197.28
    },
    {
      "time_sec": 65.13830857630819,
      "power_w": 167.27
    },
    {
      "time_sec": 65.66137632448226,
      "power_w": 188.12
    },
    {
      "time_sec": 66.18360721040517,
      "power_w": 173.56
    },
    {
      "time_sec": 66.72637908440083,
      "power_w": 116.19
    },
    {
      "time_sec": 67.24937804415822,
      "power_w": 119.96
    },
    {
      "time_sec": 67.7729481747374,
      "power_w": 145.26
    },
    {
      "time_sec": 68.29613758251071,
      "power_w": 164.44
    },
    {
      "time_sec": 68.81969590205699,
      "power_w": 185.74
    },
    {
      "time_sec": 69.34281226526946,
      "power_w": 189.67
    },
    {
      "time_sec": 69.8659185944125,
      "power_w": 154.33
    },
    {
      "time_sec": 70.38903807941824,
      "power_w": 156.21
    },
    {
      "time_sec": 70.91209427919239,
      "power_w": 157.86
    },
    {
      "time_sec": 71.43399244081229,
      "power_w": 166.76
    },
    {
      "time_sec": 71.95708721224219,
      "power_w": 181.37
    },
    {
      "time_sec": 72.47914460022002,
      "power_w": 189.91
    },
    {
      "time_sec": 73.00072348117828,
      "power_w": 204.24
    },
    {
      "time_sec": 73.52343544270843,
      "power_w": 192.99
    },
    {
      "time_sec": 74.04596029035747,
      "power_w": 170.35
    },
    {
      "time_sec": 74.56827350147069,
      "power_w": 170.68
    },
    {
      "time_sec": 75.09092902392149,
      "power_w": 192.09
    },
    {
      "time_sec": 75.61414874531329,
      "power_w": 205.3
    },
    {
      "time_sec": 76.13774025440216,
      "power_w": 191.4
    },
    {
      "time_sec": 76.66068154200912,
      "power_w": 177.93
    },
    {
      "time_sec": 77.18441451899707,
      "power_w": 177.44
    },
    {
      "time_sec": 77.70613417029381,
      "power_w": 187.55
    },
    {
      "time_sec": 78.2279448909685,
      "power_w": 179.81
    },
    {
      "time_sec": 78.74942410551012,
      "power_w": 188.93
    },
    {
      "time_sec": 79.29308156203479,
      "power_w": 174.5
    },
    {
      "time_sec": 79.81548241898417,
      "power_w": 125.53
    },
    {
      "time_sec": 80.33955543302,
      "power_w": 125.81
    },
    {
      "time_sec": 80.86284746602178,
      "power_w": 159.86
    },
    {
      "time_sec": 81.38540957123041,
      "power_w": 189.11
    },
    {
      "time_sec": 81.91026101447642,
      "power_w": 176.84
    },
    {
      "time_sec": 82.4323705136776,
      "power_w": 141.07
    },
    {
      "time_sec": 82.95455018430948,
      "power_w": 113.94
    },
    {
      "time_sec": 83.47630389779806,
      "power_w": 112.67
    },
    {
      "time_sec": 83.99888710211962,
      "power_w": 114.64
    }
  ]
}